vstc
