Metadata-Version: 2.1
Name: vstc
Version: 1.0.1
Summary: SpirentTestCenter API
Home-page: https://github.com/dvdface/vstc
Author: Ding Yi
Author-email: dvdface@hotmail.com
License: MIT
Platform: UNKNOWN
Classifier: Programming Language :: Python :: 3
Classifier: License :: OSI Approved :: MIT License
Classifier: Operating System :: OS Independent
Requires-Python: >=3.6
